lightstep/__init__.py
lightstep/b3_propagator.py
lightstep/collector_pb2.py
lightstep/constants.py
lightstep/converter.py
lightstep/http_connection.py
lightstep/http_converter.py
lightstep/lightstep_binary_propagator.py
lightstep/lightstep_carrier_pb2.py
lightstep/propagation.py
lightstep/recorder.py
lightstep/thrift_connection.py
lightstep/thrift_converter.py
lightstep/trace_context.py
lightstep/tracer.py
lightstep/util.py
lightstep/version.py
lightstep/crouton/ReportingService.py
lightstep/crouton/__init__.py
lightstep/crouton/constants.py
lightstep/crouton/ttypes.py
lightstep-4.4.7.dist-info/LICENSE
lightstep-4.4.7.dist-info/METADATA
lightstep-4.4.7.dist-info/WHEEL
lightstep-4.4.7.dist-info/top_level.txt
lightstep-4.4.7.dist-info/RECORD
